etched/__init__.py
etched/pytorch/__init__.py
etched/pytorch/frontend.py
etched/pytorch/func_groups.py
etched/pytorch/iir.py
etched/pytorch/module.py
etched/pytorch/te_equivalent.py
etched/pytorch/torch_equivalent.py
etched/pytorch/transformations.py
etched/pytorch/utils.py
etched-0.1.2.dist-info/METADATA
etched-0.1.2.dist-info/WHEEL
etched-0.1.2.dist-info/top_level.txt
etched-0.1.2.dist-info/RECORD
